allpy/__init__.py
pycontests/__init__.py
allpy-0.1.1.dist-info/LICENSE
allpy-0.1.1.dist-info/METADATA
allpy-0.1.1.dist-info/WHEEL
allpy-0.1.1.dist-info/top_level.txt
allpy-0.1.1.dist-info/RECORD
