Metadata-Version: 2.1
Name: allpy
Version: 0.1.1
Summary: Estimate the mixed strategy equilibrium of All-Pay Contests with Spillovers
Home-page: https://github.com/mwt/allpy
Author: Matthew Wildrick Thomas
Author-email: matthew.thomas@northwestern.edu
License: MIT License
Project-URL: Bug Tracker, https://github.com/mwt/allpy/issues
Platform: OS Independent
Classifier: Programming Language :: Python :: 3
Classifier: License :: OSI Approved :: MIT License
Classifier: Operating System :: OS Independent
Requires-Python: >=3.4
Requires-Dist: numpy
Requires-Dist: scipy
